mecode_viewer/__init__.py
mecode_viewer/cli.py
mecode_viewer/mecode_viewer.py
mecode_viewer-0.3.14.dist-info/METADATA
mecode_viewer-0.3.14.dist-info/WHEEL
mecode_viewer-0.3.14.dist-info/entry_points.txt
mecode_viewer-0.3.14.dist-info/licenses/LICENSE
mecode_viewer-0.3.14.dist-info/RECORD
