Metadata-Version: 2.1
Name: mecode-viewer
Version: 0.3.14
Summary: Simple GCode Viewer
Project-URL: Homepage, https://github.com/rtellez700/mecode_viewer
Author-email: Rodrigo Telles <rtelles@g.harvard.edu>
License-Expression: MIT
License-File: LICENSE
Keywords: mecode_viewer
Classifier: Development Status :: 2 - Pre-Alpha
Classifier: Intended Audience :: Developers
Classifier: License :: OSI Approved :: MIT License
Classifier: Natural Language :: English
Classifier: Programming Language :: Python :: 3.10
Classifier: Programming Language :: Python :: 3.11
Classifier: Programming Language :: Python :: 3.12
Classifier: Programming Language :: Python :: 3.13
Requires-Python: >=3.6
Requires-Dist: gcode-helpers>=0.3.0
Requires-Dist: matplotlib
Requires-Dist: numpy
Requires-Dist: vpython
